ckanext_gpkg_view-0.0.3-py3.11-nspkg.pth
ckanext/gpkg_view/__init__.py
ckanext/gpkg_view/cache.py
ckanext/gpkg_view/config.py
ckanext/gpkg_view/helpers.py
ckanext/gpkg_view/plugin.py
ckanext/gpkg_view/views.py
ckanext/gpkg_view/assets/webassets.yml
ckanext/gpkg_view/assets/css/gpkg-view.css
ckanext/gpkg_view/assets/js/common_map.js
ckanext/gpkg_view/assets/js/gpkg-view.js
ckanext/gpkg_view/assets/js/vendor/leaflet-providers.js
ckanext/gpkg_view/assets/js/vendor/leaflet/leaflet.css
ckanext/gpkg_view/assets/js/vendor/leaflet/leaflet.js
ckanext/gpkg_view/assets/js/vendor/proj4/proj4.js
ckanext/gpkg_view/assets/js/vendor/proj4leaflet/proj4leaflet.js
ckanext/gpkg_view/public/.gitignore
ckanext/gpkg_view/public/images/layers-2x.png
ckanext/gpkg_view/public/images/layers.png
ckanext/gpkg_view/public/images/marker-icon-2x.png
ckanext/gpkg_view/public/images/marker-icon.png
ckanext/gpkg_view/public/images/marker-shadow.png
ckanext/gpkg_view/templates/geopkg_view/geopkg_preview.html
ckanext_gpkg_view-0.0.3.dist-info/licenses/LICENSE
ckanext_gpkg_view-0.0.3.dist-info/METADATA
ckanext_gpkg_view-0.0.3.dist-info/WHEEL
ckanext_gpkg_view-0.0.3.dist-info/entry_points.txt
ckanext_gpkg_view-0.0.3.dist-info/namespace_packages.txt
ckanext_gpkg_view-0.0.3.dist-info/top_level.txt
ckanext_gpkg_view-0.0.3.dist-info/RECORD
