Metadata-Version: 2.4
Name: ckanext-gpkg-view
Version: 0.0.3
Summary: Preview for gpkg files
Author: DataShades
License: AGPL
Project-URL: Homepage, https://github.com/DataShades/ckanext-gpkg-view
Keywords: CKAN
Classifier: Development Status :: 4 - Beta
Classifier: License :: OSI Approved :: GNU Affero General Public License v3 or later (AGPLv3+)
Classifier: Programming Language :: Python :: 3.8
Classifier: Programming Language :: Python :: 3.9
Classifier: Programming Language :: Python :: 3.10
License-File: LICENSE
Requires-Dist: geopandas<2.0.0,>=1.0.1
Dynamic: license-file
